spql/__init__.py
spql/cli.py
spql-0.0.1.dist-info/LICENSE
spql-0.0.1.dist-info/METADATA
spql-0.0.1.dist-info/WHEEL
spql-0.0.1.dist-info/entry_points.txt
spql-0.0.1.dist-info/top_level.txt
spql-0.0.1.dist-info/RECORD
